logger/__init__.py
logger/core.py
logger_ysy-0.1.0.dist-info/METADATA
logger_ysy-0.1.0.dist-info/WHEEL
logger_ysy-0.1.0.dist-info/top_level.txt
logger_ysy-0.1.0.dist-info/RECORD
