Metadata-Version: 2.4
Name: logger_ysy
Version: 0.1.0
Summary: 即导即用的Python日志工具包，支持控制台+文件双输出，可灵活覆盖默认配置
Author-email: ysy <3100507985@qq.com>
Classifier: Programming Language :: Python :: 3
Classifier: Programming Language :: Python :: 3.8
Classifier: Programming Language :: Python :: 3.9
Classifier: Programming Language :: Python :: 3.10
Classifier: Programming Language :: Python :: 3.11
Classifier: License :: OSI Approved :: MIT License
Classifier: Operating System :: OS Independent
Requires-Python: >=3.8
